AUTHORS
LICENSE
MANIFEST.in
README.rst
setup.py
Eve_Swagger.egg-info/PKG-INFO
Eve_Swagger.egg-info/SOURCES.txt
Eve_Swagger.egg-info/dependency_links.txt
Eve_Swagger.egg-info/pbr.json
Eve_Swagger.egg-info/requires.txt
Eve_Swagger.egg-info/top_level.txt
eve_swagger/__init__.py
eve_swagger/definitions.py
eve_swagger/objects.py
eve_swagger/paths.py
eve_swagger/swagger.py
eve_swagger/validation.py
eve_swagger/templates/index.html
eve_swagger/tests/__init__.py
eve_swagger/tests/test_settings.py
eve_swagger/tests/tests.py