Metadata-Version: 2.1
Name: Eve-Swagger
Version: 0.2.0
Summary: Swagger extension for Eve powered RESTful APIs
Home-page: http://github.com/pyeve/eve-swagger
Author: Nicola Iarocci
Author-email: nicola@nicolaiarocci.com
License: BSD
Project-URL: Documentation, http://python-eve.org
Project-URL: Code, https://github.com/pyeve/eve-swagger
Project-URL: Issue tracker, https://github.com/pyeve/eve-swagger/issues
Keywords: swagger,eve,rest,api
Platform: any
Classifier: Development Status :: 4 - Beta
Classifier: Intended Audience :: Developers
Classifier: Natural Language :: English
Classifier: License :: OSI Approved :: BSD License
Classifier: Operating System :: OS Independent
Classifier: Programming Language :: Python
Classifier: Programming Language :: Python :: 2
Classifier: Programming Language :: Python :: 2.7
Classifier: Programming Language :: Python :: 3
Classifier: Programming Language :: Python :: 3.5
Classifier: Programming Language :: Python :: 3.6
Classifier: Programming Language :: Python :: 3.7
Classifier: Programming Language :: Python :: 3.8
Classifier: Programming Language :: Python :: Implementation :: CPython
Classifier: Programming Language :: Python :: Implementation :: PyPy
Requires-Python: >=2.7, !=3.0.*, !=3.1.*, !=3.2.*, !=3.3.*, !=3.4.*
Provides-Extra: docs
Provides-Extra: tests
Provides-Extra: dev
License-File: LICENSE
License-File: AUTHORS
